{"users":[{"name":"Almut","email":"almut.m.f@gmail.com","id":676264197248}],"games":[{"id":"70c28811-98b1-4f0e-b7ef-1ecc15219448","props":{"words":["Ananas","Bauernhof","Clown","Dartscheibe","Elefant","Fussball"],"players":[{"id":1,"name":"Almut","email":"email"}]},"state":{"round":0,"phase":0,"hints":[],"correctWords":[],"wrongWords":[]}},{"id":"085a567d-5065-4634-bc96-b6508b79befa","props":{"words":["Ananas","Bauernhof","Clown","Dartscheibe","Elefant","Fussball"],"players":[{"id":1,"name":"Almut","email":"email"}]},"state":{"round":0,"phase":0,"hints":[],"correctWords":[],"wrongWords":[]}}]}
